[
{"boatModel": "11 METER", "designer": "Ron Holland", "hullType": "Fin w/bulb & spade rudder", "riggingType": "Fractional  Sloop", "displacement": "3,527 lb / 1,600 kg", "loa": "33.80 ft / 10.30 m", "lwl": "26.90 ft / 8.20 m", "beam": "8.20 ft / 2.50 m", "draft": "5.90 ft / 1.80 m", "images": ["https://sailboatdata.com/storage/images/sailboat/insignia/Int_11m.gif", "https://sailboatdata.com/storage/images/sailboat/photo/11_meter_photo.jpg", "https://sailboatdata.com/storage/images/sailboat/drawing/11_meter_od_drawing.jpg"]},
{"boatModel": "517", "designer": "Christian Maury", "hullType": "Centerboard (Trunk)", "riggingType": "Fractional  Sloop", "displacement": "794 lb / 360 kg", "loa": "16.90 ft / 5.15 m", "lwl": "15.26 ft / 4.65 m", "beam": "6.10 ft / 1.86 m", "draft": "3.54 ft / 1.08 m", "images": ["https://sailboatdata.com/storage/images/sailboat/drawing/517_drawing.jpg"]},
{"boatModel": "A 27 (ARCHAMBAULT)", "designer": "Joubert-Nivelt", "hullType": "Fin w/bulb & spade rudder", "riggingType": "Fractional  Sloop", "displacement": "4,750 lb / 2,155 kg", "loa": "27.39 ft / 8.35 m", "lwl": "23.79 ft / 7.25 m", "beam": "9.78 ft / 2.98 m", "draft": "5.42 ft / 1.65 m", "images": ["https://sailboatdata.com/storage/images/sailboat/photo/a_27_archambault_photo.jpg", "https://sailboatdata.com/storage/images/sailboat/drawing/a_27_archambault_drawing.jpg"]},
{"boatModel": "ACHILLES 24", "designer": "Oliver Lee", "hullType": "Fin with rudder on skeg", "riggingType": "Masthead Sloop", "displacement": "2,600 lb / 1,179 kg", "loa": "23.75 ft / 7.24 m", "lwl": "19.50 ft / 5.94 m", "beam": "7.09 ft / 2.16 m", "draft": "3.75 ft / 1.14 m", "images": ["https://sailboatdata.com/storage/images/sailboat/insignia/achilles_24_insig.gif", "https://sailboatdata.com/storage/images/sailboat/photo/achlles_24_photo.jpg", "https://sailboatdata.com/storage/images/sailboat/drawing/Achilles_24_drawing.gif"]},
{"boatModel": "ABLE 42", "designer": "C. W.  (Chuck) Paine", "hullType": "Fin with rudder on skeg", "riggingType": "Masthead Sloop", "displacement": "21,678 lb / 9,833 kg", "loa": "42.00 ft / 12.80 m", "lwl": "32.67 ft / 9.96 m", "beam": "12.67 ft / 3.86 m", "draft": "5.17 ft / 1.58 m", "images": ["https://sailboatdata.com/storage/images/sailboat/photo/able_42_photo.jpg"]},
{"boatModel": "8M ONE DESIGN", "designer": "Doug Peterson", "hullType": "Lifting Keel", "riggingType": "Fractional  Sloop", "displacement": "2,425 lb / 1,100 kg", "loa": "26.25 ft / 8.00 m", "lwl": "22.93 ft / 6.99 m", "beam": "8.17 ft / 2.49 m", "draft": "5.58 ft / 1.70 m", "images": ["https://sailboatdata.com/storage/images/sailboat/drawing/8m_one-design_drawing.jpg"]},
{"boatModel": "707 (THOMAS)", "designer": "David Thomas", "hullType": "Lifting Keel", "riggingType": "Fractional  Sloop", "displacement": "1,980 lb / 898 kg", "loa": "23.70 ft / 7.22 m", "lwl": "23.00 ft / 7.01 m", "beam": "8.30 ft / 2.53 m", "draft": "4.95 ft / 1.51 m", "images": ["https://sailboatdata.com/storage/images/sailboat/insignia/hunter_707.gif", "https://sailboatdata.com/storage/images/sailboat/photo/hunter_707_photo.jpg", "https://sailboatdata.com/storage/images/sailboat/drawing/hunter_707_drawing.jpg"]},
{"boatModel": "707 (EDWARDSSON)", "designer": "G\u00f6sta & Gunnar Edwardsson", "hullType": "Fin w/transom hung rudder", "riggingType": "Fractional  Sloop", "displacement": "1,984 lb / 900 kg", "loa": "23.20 ft / 7.07 m", "lwl": "19.03 ft / 5.80 m", "beam": "6.73 ft / 2.05 m", "draft": "4.43 ft / 1.35 m", "images": ["https://sailboatdata.com/storage/images/sailboat/photo/707_photo.jpg", "https://sailboatdata.com/storage/images/sailboat/drawing/707_sweden_drawing.jpg"]},
{"boatModel": "AEGEAN 51", "designer": "Walter Shultz", "hullType": "Keel/Cbrd.", "riggingType": "Staysail Ketch", "displacement": "39,500 lb / 17,917 kg", "loa": "50.92 ft / 15.52 m", "lwl": "42.75 ft / 13.03 m", "beam": "14.25 ft / 4.34 m", "draft": "9.75 ft / 2.97 m", "images": ["https://sailboatdata.com/storage/images/sailboat/drawing/aegean_51_drawing.jpg"]},
{"boatModel": "AEGEAN 234", "designer": "Ed Dubois", "hullType": "Fin w/spade rudder", "riggingType": "Fractional  Sloop", "displacement": "2,685 lb / 1,218 kg", "loa": "21.70 ft / 6.61 m", "lwl": "19.20 ft / 5.85 m", "beam": "8.20 ft / 2.50 m", "draft": "4.61 ft / 1.41 m", "images": []},
{"boatModel": "ADHARA 30", "designer": "Doug Peterson", "hullType": "Fin w/spade rudder", "riggingType": "Masthead Sloop", "displacement": "4,800 lb / 2,177 kg", "loa": "29.89 ft / 9.11 m", "lwl": "25.50 ft / 7.77 m", "beam": "10.67 ft / 3.25 m", "draft": "5.75 ft / 1.75 m", "images": ["https://sailboatdata.com/storage/images/sailboat/photo/adhara_30_photo.jpg"]},
{"boatModel": "ADAMS 13", "designer": "Joe Adams", "hullType": "Keel/Cbrd.", "riggingType": "Cutter", "displacement": "14,462 lb / 6,560 kg", "loa": "43.11 ft / 13.14 m", "lwl": "40.62 ft / 12.38 m", "beam": "10.17 ft / 3.10 m", "draft": "8.76 ft / 2.67 m", "images": ["https://sailboatdata.com/storage/images/sailboat/drawing/adams_13_drawing.jpg"]},
{"boatModel": "AJAX (LEE)", "designer": "Oliver Lee", "hullType": "Fin with rudder on skeg", "riggingType": "Fractional  Sloop", "displacement": "1,900 lb / 862 kg", "loa": "23.25 ft / 7.09 m", "lwl": "19.16 ft / 5.84 m", "beam": "6.42 ft / 1.96 m", "draft": "3.67 ft / 1.12 m", "images": ["https://sailboatdata.com/storage/images/sailboat/photo/ajax_23_photo.jpg", "https://sailboatdata.com/storage/images/sailboat/drawing/ajax_23_drawing.jpg"]},
{"boatModel": "ALACRITY 670 (ALACRITY 22)", "designer": "Frank V. Butler", "hullType": "Swing Keel", "riggingType": "Masthead Sloop", "displacement": "2,250 lb / 1,021 kg", "loa": "21.50 ft / 6.55 m", "lwl": "19.33 ft / 5.89 m", "beam": "7.67 ft / 2.34 m", "draft": "3.80 ft / 1.16 m", "images": ["https://sailboatdata.com/storage/images/sailboat/drawing/alacrity_670_drawing.jpg"]},
{"boatModel": "ALBIN EXPRESS", "designer": "Peter Norlin", "hullType": "Fin w/transom hung rudder", "riggingType": "Fractional  Sloop", "displacement": "3,968 lb / 1,800 kg", "loa": "25.50 ft / 7.77 m", "lwl": "21.58 ft / 6.58 m", "beam": "8.20 ft / 2.50 m", "draft": "4.75 ft / 1.45 m", "images": ["https://sailboatdata.com/storage/images/sailboat/insignia/albin_express.gif", "https://sailboatdata.com/storage/images/sailboat/photo/albin_express_photo.jpg", "https://sailboatdata.com/storage/images/sailboat/drawing/albin_express_drawing.jpg"]},
{"boatModel": "ADAGIO 27", "designer": "Lars Olof Norlin", "hullType": "Long Keel", "riggingType": "Masthead Sloop", "displacement": "6,614 lb / 3,000 kg", "loa": "26.71 ft / 8.14 m", "lwl": "23.95 ft / 7.30 m", "beam": "9.19 ft / 2.80 m", "draft": "4.10 ft / 1.25 m", "images": ["https://sailboatdata.com/storage/images/sailboat/drawing/adagio_27_drawing.jpg"]},
{"boatModel": "ALERION 26 (CARROL MARINE)", "designer": "Nathaniel G. Herreshoff", "hullType": "Long Keel", "riggingType": "Fractional  Sloop", "displacement": "4,800 lb / 2,177 kg", "loa": "25.33 ft / 7.72 m", "lwl": "20.00 ft / 6.10 m", "beam": "7.17 ft / 2.19 m", "draft": "3.58 ft / 1.09 m", "images": ["https://sailboatdata.com/storage/images/sailboat/photo/Alerion26_photo.jpg", "https://sailboatdata.com/storage/images/sailboat/drawing/Alerion26_drawings.gif"]},
{"boatModel": "ALERION", "designer": "Nathaniel G. Herreshoff", "hullType": "Keel/Cbrd.", "riggingType": "Fractional  Sloop", "displacement": "6,050 lb / 2,744 kg", "loa": "26.00 ft / 7.92 m", "lwl": "21.75 ft / 6.63 m", "beam": "7.58 ft / 2.31 m", "draft": "5.50 ft / 1.68 m", "images": ["https://sailboatdata.com/storage/images/sailboat/drawing/alerion_26_herreshoff_drawing.jpg"]},
{"boatModel": "ADAMS 10", "designer": "Joe Adams", "hullType": "Fin w/transom hung rudder", "riggingType": "Fractional  Sloop", "displacement": "6,510 lb / 2,953 kg", "loa": "33.00 ft / 10.06 m", "lwl": "31.13 ft / 9.49 m", "beam": "8.62 ft / 2.63 m", "draft": "5.75 ft / 1.75 m", "images": ["https://sailboatdata.com/storage/images/sailboat/insignia/adams_10_insig.gif", "https://sailboatdata.com/storage/images/sailboat/photo/adam_10_photo.jpg", "https://sailboatdata.com/storage/images/sailboat/drawing/adams_10_drawing.jpg"]},
{"boatModel": "ALAJUELA 48", "designer": "Raymond Richards", "hullType": "Fin with rudder on skeg", "riggingType": "Masthead  Ketch", "displacement": "29,500 lb / 13,381 kg", "loa": "53.75 ft / 16.38 m", "lwl": "40.50 ft / 12.34 m", "beam": "13.83 ft / 4.22 m", "draft": "6.75 ft / 2.06 m", "images": []},
{"boatModel": "ALPA  A7", "designer": "John Illingworth", "hullType": "Fin Keel", "riggingType": "Masthead Sloop", "displacement": "4,850 lb / 2,200 kg", "loa": "22.97 ft / 7.00 m", "lwl": "18.86 ft / 5.75 m", "beam": "7.38 ft / 2.25 m", "draft": "3.77 ft / 1.15 m", "images": ["https://sailboatdata.com/storage/images/sailboat/drawing/alpa_a7_drawing.jpg"]},
{"boatModel": "ALBIN 57", "designer": "Rolf Magnusson", "hullType": "Swing Keel", "riggingType": "Fractional  Sloop", "displacement": "1,764 lb / 800 kg", "loa": "18.83 ft / 5.74 m", "lwl": "16.40 ft / 5.00 m", "beam": "7.91 ft / 2.41 m", "draft": "4.26 ft / 1.30 m", "images": ["https://sailboatdata.com/storage/images/sailboat/photo/albin_57_photo.jpg", "https://sailboatdata.com/storage/images/sailboat/drawing/albin_57_drawing.jpg"]},
{"boatModel": "ALERION 38", "designer": "Halsey Herreshoff", "hullType": "Fin with rudder on skeg", "riggingType": "Masthead Sloop", "displacement": "17,000 lb / 7,711 kg", "loa": "38.00 ft / 11.58 m", "lwl": "29.50 ft / 8.99 m", "beam": "10.75 ft / 3.28 m", "draft": "6.00 ft / 1.83 m", "images": ["https://sailboatdata.com/storage/images/sailboat/drawing/alerion_38_drawing.jpg"]},
{"boatModel": "ALLURES 39.9", "designer": "Berret-Racoupeau", "hullType": "Swing Keel", "riggingType": "Masthead Sloop", "displacement": "24,030 lb / 10,900 kg", "loa": "41.50 ft / 12.65 m", "lwl": "36.74 ft / 11.20 m", "beam": "13.62 ft / 4.15 m", "draft": "9.02 ft / 2.75 m", "images": ["https://sailboatdata.com/storage/images/sailboat/drawing/allures_39-9_drawing.jpg"]}
]
